weakget.py
weakget-1.0.dist-info/LICENSE
weakget-1.0.dist-info/WHEEL
weakget-1.0.dist-info/METADATA
weakget-1.0.dist-info/RECORD
