Metadata-Version: 2.1
Name: weakget
Version: 1.0
Summary: weakget - Chain multiple `getattr` and `.get` calls into one expression
Author-email: Sye van der Veen <syeberman@gmail.com>
Classifier: License :: Public Domain
Project-URL: Home, https://github.com/Syeberman/weakget
